CHANGES.rst
MANIFEST.in
Makefile
Makefile.database
Makefile.i18n
Makefile.release
README.rst
setup.py
version.txt
docs/Makefile
docs/conf.py
docs/index.rst
docs/database/domains.rst
docs/database/index.rst
docs/database/tables/activities.rst
docs/database/tables/activitypayloads.rst
docs/database/tables/availabilities.rst
docs/database/tables/check_availability_validity.sql
docs/database/tables/check_duty_validity.sql
docs/database/tables/check_edition_validity.sql
docs/database/tables/check_task_validity.sql
docs/database/tables/duties.rst
docs/database/tables/dutypayloads.rst
docs/database/tables/editions.rst
docs/database/tables/index.rst
docs/database/tables/locations.rst
docs/database/tables/personactivities.rst
docs/database/tables/persons.rst
docs/database/tables/task_events.sql
docs/database/tables/task_timeline.sql
docs/database/tables/tasks.rst
hurm.db.egg-info/PKG-INFO
hurm.db.egg-info/SOURCES.txt
hurm.db.egg-info/dependency_links.txt
hurm.db.egg-info/namespace_packages.txt
hurm.db.egg-info/not-zip-safe
hurm.db.egg-info/requires.txt
hurm.db.egg-info/top_level.txt
hurm/db/__init__.py
hurm/db/utils.py
hurm/db/data/2015.yaml.gpg
hurm/db/data/hurm.axon
hurm/db/data/preload.py
hurm/db/data/test.yaml
hurm/db/entities/__init__.py
hurm/db/entities/activity.py
hurm/db/entities/activitypayload.py
hurm/db/entities/availability.py
hurm/db/entities/duty.py
hurm/db/entities/dutypayload.py
hurm/db/entities/edition.py
hurm/db/entities/location.py
hurm/db/entities/person.py
hurm/db/entities/personactivity.py
hurm/db/entities/task.py
hurm/db/locale/hurm-db.cfg
hurm/db/locale/hurm-db.pot
hurm/db/locale/it/LC_MESSAGES/hurm-db.mo
hurm/db/locale/it/LC_MESSAGES/hurm-db.po
hurm/db/tables/__init__.py
hurm/db/tables/activities.py
hurm/db/tables/activitypayloads.py
hurm/db/tables/availabilities.py
hurm/db/tables/domains.py
hurm/db/tables/duties.py
hurm/db/tables/dutypayloads.py
hurm/db/tables/editions.py
hurm/db/tables/locations.py
hurm/db/tables/personactivities.py
hurm/db/tables/persons.py
hurm/db/tables/tasks.py
tests/conftest.py
tests/test_availability.py
tests/test_duty.py
tests/test_edition.py
tests/test_person.py
tests/test_task.py
tests/test_utils.py