Metadata-Version: 1.1
Name: hurm.db
Version: 0.10
Summary: Human Resources Manager, database definition
Home-page: https://bitbucket.org/lele/hurm.db
Author: Lele Gaifax
Author-email: lele@metapensiero.it
License: GPLv3+
Keywords: sqlalchemy postgresql
Platform: UNKNOWN
Classifier: Development Status :: 3 - Alpha
Classifier: Programming Language :: Python
Classifier: Programming Language :: Python :: 3
Classifier: Programming Language :: Python :: 3.5
Classifier: License :: OSI Approved :: GNU General Public License v3 or later (GPLv3+)
